calculator/__init__.py
calculator/command_line.py
calculator/distance_calc.py
calculator/osm_coordinate.py
calculator/tests/__init__.py
calculator/tests/test_distance_calc.py
distances_calculator/__init__.py
distances_calculator/command_line.py
distances_calculator/distance_calc.py
distances_calculator/osm_coordinate.py
distances_calculator/write_into_table.py
distances_calculator/tests/__init__.py
distances_calculator/tests/my_test.py
distances_calculator/tests/test_distance_calc.py
distances_calculator-0.1.3.dist-info/METADATA
distances_calculator-0.1.3.dist-info/RECORD
distances_calculator-0.1.3.dist-info/WHEEL
distances_calculator-0.1.3.dist-info/entry_points.txt
distances_calculator-0.1.3.dist-info/top_level.txt
