Metadata-Version: 2.1
Name: distances-calculator
Version: 0.1.3
Summary: Calculate distances between 2 addresses, Distances Calculator is based on open street map api.
Home-page: https://github.com/tim-hub/distances_calculator
Author: tim-hub
License: UNKNOWN
Keywords: distance distances_calculator,open street map,csv,big data
Platform: UNKNOWN
Classifier: Programming Language :: Python :: 3
Classifier: License :: OSI Approved :: MIT License
Classifier: Operating System :: OS Independent
Requires-Dist: requests
Requires-Dist: pandas
Requires-Dist: argparse
